cas.py
python_cas_mb-1.5.1.dist-info/LICENSE.txt
python_cas_mb-1.5.1.dist-info/METADATA
python_cas_mb-1.5.1.dist-info/WHEEL
python_cas_mb-1.5.1.dist-info/top_level.txt
python_cas_mb-1.5.1.dist-info/RECORD
