Metadata-Version: 2.1
Name: python-cas-mb
Version: 1.5.1
Summary: Python CAS client library
Home-page: https://github.com/mbenadda/python-cas
Author: Ming Chen
Author-email: ming@djangocas.dev
License: MIT
Download-URL: https://github.com/mbenadda/python-cas/releases
Keywords: cas,cas2,cas3,client,sso,single sign-on,authentication,auth
Platform: UNKNOWN
Classifier: Development Status :: 5 - Production/Stable
Classifier: Environment :: Web Environment
Classifier: Intended Audience :: Developers
Classifier: License :: OSI Approved :: MIT License
Classifier: Natural Language :: English
Classifier: Operating System :: OS Independent
Classifier: Programming Language :: Python
Classifier: Programming Language :: Python :: 2
Classifier: Programming Language :: Python :: 2.7
Classifier: Programming Language :: Python :: 3
Classifier: Programming Language :: Python :: 3.5
Classifier: Programming Language :: Python :: 3.6
Classifier: Programming Language :: Python :: 3.7
Classifier: Programming Language :: Python :: 3.8
Classifier: Topic :: Internet :: WWW/HTTP
Requires-Python: >=2.7, !=3.0.*, !=3.1.*, !=3.2.*, !=3.3.*, !=3.4.*
Requires-Dist: six (>=1.10.0)
Requires-Dist: requests (>=2.11.1)
Requires-Dist: lxml (>=3.4)
